{
  "version": "V9 Graph-DTES Operator",
  "input": "runs/dtes_spectral_input.json",
  "steps": 3000,
  "k": 50,
  "sigma_t": 5.0,
  "energy_beta": 1.0,
  "k_neighbors": 12,
  "max_n": 800,
  "n_nodes": 800,
  "laplacian_type": "normalized",
  "spectral_calibration": true,
  "smooth_weight": 0.01,
  "amplitude_weight": 0.001,
  "final_loss": 0.05221571773290634,
  "final_spectral_loss": 0.00035064422991126776,
  "final_spacing_loss": 0.08902397751808167,
  "edge_scale": 0.4139653146266937,
  "spectral_scale": 0.7310484647750854,
  "spectral_shift": -0.015460081398487091,
  "outputs": {
    "potential": "runs/graph_dtes_v9_potential.npy",
    "eigenvalues_raw": "runs/graph_dtes_v9_eigenvalues_raw.csv",
    "eigenvalues_scaled": "runs/graph_dtes_v9_eigenvalues_scaled.csv",
    "adjacency": "runs/graph_dtes_v9_adjacency.npy",
    "operator": "runs/graph_dtes_v9_operator.npy",
    "loss_curve": "runs/graph_dtes_v9_loss_curve.csv",
    "plots": [
      "runs/graph_dtes_v9_loss.png",
      "runs/graph_dtes_v9_potential.png",
      "runs/graph_dtes_v9_spectrum_scaled.png",
      "runs/graph_dtes_v9_adjacency.png"
    ]
  },
  "history": [
    {
      "step": 0,
      "loss": 0.7902258634567261,
      "spectral_loss": 0.08114569634199142,
      "spacing_loss": 1.2511708736419678,
      "smoothness_loss": 8.249473571777344,
      "amplitude_loss": 1.0,
      "edge_scale": 1.0,
      "spectral_scale": 1.0,
      "spectral_shift": -0.0009979071328416467
    },
    {
      "step": 50,
      "loss": 0.22767992317676544,
      "spectral_loss": 0.007359722629189491,
      "spacing_loss": 0.2823590636253357,
      "smoothness_loss": 7.816162109375,
      "amplitude_loss": 0.9790441393852234,
      "edge_scale": 1.0002596378326416,
      "spectral_scale": 0.967448353767395,
      "spectral_shift": 0.0035652942024171352
    },
    {
      "step": 100,
      "loss": 0.17323513329029083,
      "spectral_loss": 0.0006695689517073333,
      "spacing_loss": 0.19510218501091003,
      "smoothness_loss": 7.405239105224609,
      "amplitude_loss": 0.9620912671089172,
      "edge_scale": 0.982238233089447,
      "spectral_scale": 0.9394373893737793,
      "spectral_shift": 0.003171982243657112
    },
    {
      "step": 150,
      "loss": 0.16198258101940155,
      "spectral_loss": 0.0006073607364669442,
      "spacing_loss": 0.18054835498332977,
      "smoothness_loss": 7.015201568603516,
      "amplitude_loss": 0.9490306377410889,
      "edge_scale": 0.9699855446815491,
      "spectral_scale": 0.9130004644393921,
      "spectral_shift": 0.0012211315333843231
    },
    {
      "step": 200,
      "loss": 0.14786800742149353,
      "spectral_loss": 0.0003699291846714914,
      "spacing_loss": 0.16016457974910736,
      "smoothness_loss": 6.647580146789551,
      "amplitude_loss": 0.9399998188018799,
      "edge_scale": 0.945054829120636,
      "spectral_scale": 0.8931421637535095,
      "spectral_shift": -0.00234523368999362
    },
    {
      "step": 250,
      "loss": 0.1372753530740738,
      "spectral_loss": 0.00048718880861997604,
      "spacing_loss": 0.14570632576942444,
      "smoothness_loss": 6.300020217895508,
      "amplitude_loss": 0.9347983002662659,
      "edge_scale": 0.9198222160339355,
      "spectral_scale": 0.8698192834854126,
      "spectral_shift": -0.0012329760938882828
    },
    {
      "step": 300,
      "loss": 0.14361289143562317,
      "spectral_loss": 0.00031912943813949823,
      "spacing_loss": 0.16529850661754608,
      "smoothness_loss": 5.9711527824401855,
      "amplitude_loss": 0.9329708814620972,
      "edge_scale": 0.8955867886543274,
      "spectral_scale": 0.8573963046073914,
      "spectral_shift": 0.0035055570770055056
    },
    {
      "step": 350,
      "loss": 0.1456591635942459,
      "spectral_loss": 0.0005554524250328541,
      "spacing_loss": 0.17512507736682892,
      "smoothness_loss": 5.660668849945068,
      "amplitude_loss": 0.9344790577888489,
      "edge_scale": 0.8686503767967224,
      "spectral_scale": 0.8505440950393677,
      "spectral_shift": -0.012561731971800327
    },
    {
      "step": 400,
      "loss": 0.1337217092514038,
      "spectral_loss": 0.00038674150709994137,
      "spacing_loss": 0.1574707180261612,
      "smoothness_loss": 5.366074085235596,
      "amplitude_loss": 0.9388607740402222,
      "edge_scale": 0.8498283624649048,
      "spectral_scale": 0.8400008678436279,
      "spectral_shift": -0.006247187033295631
    },
    {
      "step": 450,
      "loss": 0.1238546296954155,
      "spectral_loss": 0.00036397704388946295,
      "spacing_loss": 0.14332687854766846,
      "smoothness_loss": 5.088108062744141,
      "amplitude_loss": 0.9461355805397034,
      "edge_scale": 0.8281318545341492,
      "spectral_scale": 0.8410828709602356,
      "spectral_shift": -0.005539563484489918
    },
    {
      "step": 500,
      "loss": 0.1303601861000061,
      "spectral_loss": 0.0003828146727755666,
      "spacing_loss": 0.16153614223003387,
      "smoothness_loss": 4.825329303741455,
      "amplitude_loss": 0.95599764585495,
      "edge_scale": 0.8085695505142212,
      "spectral_scale": 0.8295921683311462,
      "spectral_shift": -0.00419953279197216
    },
    {
      "step": 550,
      "loss": 0.1366921365261078,
      "spectral_loss": 0.00039227434899657965,
      "spacing_loss": 0.1791280210018158,
      "smoothness_loss": 4.576767444610596,
      "amplitude_loss": 0.9681944251060486,
      "edge_scale": 0.7920701503753662,
      "spectral_scale": 0.8181467056274414,
      "spectral_shift": 0.005653918255120516
    },
    {
      "step": 600,
      "loss": 0.11899784207344055,
      "spectral_loss": 0.0003763245767913759,
      "spacing_loss": 0.1484278291463852,
      "smoothness_loss": 4.342496871948242,
      "amplitude_loss": 0.9826422333717346,
      "edge_scale": 0.7736117243766785,
      "spectral_scale": 0.8207587599754333,
      "spectral_shift": 0.014055744744837284
    },
    {
      "step": 650,
      "loss": 0.12206735461950302,
      "spectral_loss": 0.0003729595337063074,
      "spacing_loss": 0.15896347165107727,
      "smoothness_loss": 4.121354579925537,
      "amplitude_loss": 0.9991138577461243,
      "edge_scale": 0.75510573387146,
      "spectral_scale": 0.8106160759925842,
      "spectral_shift": 0.016343390569090843
    },
    {
      "step": 700,
      "loss": 0.11256789416074753,
      "spectral_loss": 0.0003709521552082151,
      "spacing_loss": 0.14411072432994843,
      "smoothness_loss": 3.912416934967041,
      "amplitude_loss": 1.0174118280410767,
      "edge_scale": 0.7380825281143188,
      "spectral_scale": 0.8155778646469116,
      "spectral_shift": 0.004313390702009201
    },
    {
      "step": 750,
      "loss": 0.10829617083072662,
      "spectral_loss": 0.0003071388928219676,
      "spacing_loss": 0.13960036635398865,
      "smoothness_loss": 3.7151458263397217,
      "amplitude_loss": 1.0373940467834473,
      "edge_scale": 0.7220733761787415,
      "spectral_scale": 0.8227924108505249,
      "spectral_shift": -0.005743080750107765
    },
    {
      "step": 800,
      "loss": 0.10593263059854507,
      "spectral_loss": 0.000367455038940534,
      "spacing_loss": 0.13843242824077606,
      "smoothness_loss": 3.529010772705078,
      "amplitude_loss": 1.0588550567626953,
      "edge_scale": 0.7058019042015076,
      "spectral_scale": 0.8224472403526306,
      "spectral_shift": -0.010000977665185928
    },
    {
      "step": 850,
      "loss": 0.10190018266439438,
      "spectral_loss": 0.00042988776112906635,
      "spacing_loss": 0.1337108165025711,
      "smoothness_loss": 3.3533248901367188,
      "amplitude_loss": 1.081641435623169,
      "edge_scale": 0.6908804178237915,
      "spectral_scale": 0.8202136754989624,
      "spectral_shift": -0.011153953149914742
    },
    {
      "step": 900,
      "loss": 0.09263189882040024,
      "spectral_loss": 0.00034610225702635944,
      "spacing_loss": 0.11860688775777817,
      "smoothness_loss": 3.1876609325408936,
      "amplitude_loss": 1.1057461500167847,
      "edge_scale": 0.6734916567802429,
      "spectral_scale": 0.8216095566749573,
      "spectral_shift": -0.012549733743071556
    },
    {
      "step": 950,
      "loss": 0.11105058342218399,
      "spectral_loss": 0.00037436257116496563,
      "spacing_loss": 0.15847693383693695,
      "smoothness_loss": 3.0306930541992188,
      "amplitude_loss": 1.1308284997940063,
      "edge_scale": 0.6609304547309875,
      "spectral_scale": 0.8200583457946777,
      "spectral_shift": -0.01236304547637701
    },
    {
      "step": 1000,
      "loss": 0.10250617563724518,
      "spectral_loss": 0.0003065513737965375,
      "spacing_loss": 0.1444348841905594,
      "smoothness_loss": 2.8825290203094482,
      "amplitude_loss": 1.1568922996520996,
      "edge_scale": 0.6479364037513733,
      "spectral_scale": 0.8189408779144287,
      "spectral_shift": -0.018568668514490128
    },
    {
      "step": 1050,
      "loss": 0.0919245034456253,
      "spectral_loss": 0.00033667683601379395,
      "spacing_loss": 0.12595294415950775,
      "smoothness_loss": 2.742755174636841,
      "amplitude_loss": 1.1838067770004272,
      "edge_scale": 0.634141206741333,
      "spectral_scale": 0.8124077916145325,
      "spectral_shift": -0.010890149511396885
    },
    {
      "step": 1100,
      "loss": 0.09392024576663971,
      "spectral_loss": 0.00039164870395325124,
      "spacing_loss": 0.1324247121810913,
      "smoothness_loss": 2.610487699508667,
      "amplitude_loss": 1.2113702297210693,
      "edge_scale": 0.6227965950965881,
      "spectral_scale": 0.8102096319198608,
      "spectral_shift": -0.0002796064654830843
    },
    {
      "step": 1150,
      "loss": 0.09578786790370941,
      "spectral_loss": 0.000450125866336748,
      "spacing_loss": 0.13848468661308289,
      "smoothness_loss": 2.4855849742889404,
      "amplitude_loss": 1.2395505905151367,
      "edge_scale": 0.611233651638031,
      "spectral_scale": 0.8064207434654236,
      "spectral_shift": -0.004364312626421452
    },
    {
      "step": 1200,
      "loss": 0.07237108051776886,
      "spectral_loss": 0.00035945564741268754,
      "spacing_loss": 0.09414084255695343,
      "smoothness_loss": 2.3673033714294434,
      "amplitude_loss": 1.268174409866333,
      "edge_scale": 0.6021063923835754,
      "spectral_scale": 0.7992106080055237,
      "spectral_shift": -0.011162171140313148
    },
    {
      "step": 1250,
      "loss": 0.08183783292770386,
      "spectral_loss": 0.00028862725594080985,
      "spacing_loss": 0.11538912355899811,
      "smoothness_loss": 2.2557382583618164,
      "amplitude_loss": 1.2972619533538818,
      "edge_scale": 0.5910746455192566,
      "spectral_scale": 0.7992637753486633,
      "spectral_shift": -0.012524273246526718
    },
    {
      "step": 1300,
      "loss": 0.07655444741249084,
      "spectral_loss": 0.00037040855386294425,
      "spacing_loss": 0.10671573132276535,
      "smoothness_loss": 2.1499550342559814,
      "amplitude_loss": 1.3266208171844482,
      "edge_scale": 0.5830218195915222,
      "spectral_scale": 0.7942742705345154,
      "spectral_shift": -0.00654034037142992
    },
    {
      "step": 1350,
      "loss": 0.07938560843467712,
      "spectral_loss": 0.000395178678445518,
      "spacing_loss": 0.11427131295204163,
      "smoothness_loss": 2.049856424331665,
      "amplitude_loss": 1.3562082052230835,
      "edge_scale": 0.575782299041748,
      "spectral_scale": 0.7955345511436462,
      "spectral_shift": -0.003755665849894285
    },
    {
      "step": 1400,
      "loss": 0.07842045277357101,
      "spectral_loss": 0.00035900293732993305,
      "spacing_loss": 0.11425232142210007,
      "smoothness_loss": 1.9549401998519897,
      "amplitude_loss": 1.3858894109725952,
      "edge_scale": 0.5714206099510193,
      "spectral_scale": 0.805901050567627,
      "spectral_shift": -0.007977085188031197
    },
    {
      "step": 1450,
      "loss": 0.07062041759490967,
      "spectral_loss": 0.0004172491608187556,
      "spacing_loss": 0.10026591271162033,
      "smoothness_loss": 1.8654444217681885,
      "amplitude_loss": 1.4157730340957642,
      "edge_scale": 0.5631962418556213,
      "spectral_scale": 0.8067107796669006,
      "spectral_shift": -0.01707691326737404
    },
    {
      "step": 1500,
      "loss": 0.05981473997235298,
      "spectral_loss": 0.00035158253740519285,
      "spacing_loss": 0.08042418956756592,
      "smoothness_loss": 1.7805417776107788,
      "amplitude_loss": 1.4456467628479004,
      "edge_scale": 0.5576209425926208,
      "spectral_scale": 0.7974839210510254,
      "spectral_shift": -0.01634080335497856
    },
    {
      "step": 1550,
      "loss": 0.07474882900714874,
      "spectral_loss": 0.00033496267860755324,
      "spacing_loss": 0.11187196522951126,
      "smoothness_loss": 1.7002333402633667,
      "amplitude_loss": 1.4755510091781616,
      "edge_scale": 0.5510309934616089,
      "spectral_scale": 0.7999892234802246,
      "spectral_shift": -0.018892250955104828
    },
    {
      "step": 1600,
      "loss": 0.07885907590389252,
      "spectral_loss": 0.0003597818431444466,
      "spacing_loss": 0.121507428586483,
      "smoothness_loss": 1.6240204572677612,
      "amplitude_loss": 1.505373239517212,
      "edge_scale": 0.5458256006240845,
      "spectral_scale": 0.7969422936439514,
      "spectral_shift": -0.01589449681341648
    },
    {
      "step": 1650,
      "loss": 0.06598880887031555,
      "spectral_loss": 0.00033964947215281427,
      "spacing_loss": 0.09719420224428177,
      "smoothness_loss": 1.5517044067382812,
      "amplitude_loss": 1.5350167751312256,
      "edge_scale": 0.54259192943573,
      "spectral_scale": 0.7900705933570862,
      "spectral_shift": -0.01125504169613123
    },
    {
      "step": 1700,
      "loss": 0.07623986899852753,
      "spectral_loss": 0.0003162197826895863,
      "spacing_loss": 0.11905308067798615,
      "smoothness_loss": 1.4832597970962524,
      "amplitude_loss": 1.5645081996917725,
      "edge_scale": 0.5382347702980042,
      "spectral_scale": 0.78862065076828,
      "spectral_shift": -0.022715149447321892
    },
    {
      "step": 1750,
      "loss": 0.06652095913887024,
      "spectral_loss": 0.0003525166248437017,
      "spacing_loss": 0.10077981650829315,
      "smoothness_loss": 1.4184730052947998,
      "amplitude_loss": 1.5938043594360352,
      "edge_scale": 0.5326654314994812,
      "spectral_scale": 0.7825937271118164,
      "spectral_shift": -0.019704505801200867
    },
    {
      "step": 1800,
      "loss": 0.0720653086900711,
      "spectral_loss": 0.0003949305391870439,
      "spacing_loss": 0.11295654624700546,
      "smoothness_loss": 1.3569239377975464,
      "amplitude_loss": 1.6228671073913574,
      "edge_scale": 0.5279074311256409,
      "spectral_scale": 0.76611328125,
      "spectral_shift": -0.01283337827771902
    },
    {
      "step": 1850,
      "loss": 0.05886998027563095,
      "spectral_loss": 0.00032562026171945035,
      "spacing_loss": 0.08781623840332031,
      "smoothness_loss": 1.298460602760315,
      "amplitude_loss": 1.651637077331543,
      "edge_scale": 0.5236034989356995,
      "spectral_scale": 0.7577660083770752,
      "spectral_shift": -0.009321015328168869
    },
    {
      "step": 1900,
      "loss": 0.06502784788608551,
      "spectral_loss": 0.00037819211138412356,
      "spacing_loss": 0.10107873380184174,
      "smoothness_loss": 1.2430230379104614,
      "amplitude_loss": 1.6800602674484253,
      "edge_scale": 0.5194504261016846,
      "spectral_scale": 0.7609410285949707,
      "spectral_shift": -0.019803140312433243
    },
    {
      "step": 1950,
      "loss": 0.063553586602211,
      "spectral_loss": 0.0003507790679577738,
      "spacing_loss": 0.0991792306303978,
      "smoothness_loss": 1.1904988288879395,
      "amplitude_loss": 1.708201289176941,
      "edge_scale": 0.5128843188285828,
      "spectral_scale": 0.7648999691009521,
      "spectral_shift": -0.028441043570637703
    },
    {
      "step": 2000,
      "loss": 0.05332464352250099,
      "spectral_loss": 0.0003448653733357787,
      "spacing_loss": 0.07967882603406906,
      "smoothness_loss": 1.1404457092285156,
      "amplitude_loss": 1.7359085083007812,
      "edge_scale": 0.5084003806114197,
      "spectral_scale": 0.7596385478973389,
      "spectral_shift": -0.03025318868458271
    },
    {
      "step": 2050,
      "loss": 0.07426464557647705,
      "spectral_loss": 0.0003955542342737317,
      "spacing_loss": 0.12235216051340103,
      "smoothness_loss": 1.0929821729660034,
      "amplitude_loss": 1.7631850242614746,
      "edge_scale": 0.503312349319458,
      "spectral_scale": 0.7578557133674622,
      "spectral_shift": -0.023074831813573837
    },
    {
      "step": 2100,
      "loss": 0.06527791172266006,
      "spectral_loss": 0.00040447685751132667,
      "spacing_loss": 0.1052100881934166,
      "smoothness_loss": 1.047838807106018,
      "amplitude_loss": 1.7900041341781616,
      "edge_scale": 0.4977564215660095,
      "spectral_scale": 0.7598066329956055,
      "spectral_shift": -0.015668652951717377
    },
    {
      "step": 2150,
      "loss": 0.06799476593732834,
      "spectral_loss": 0.00034454220440238714,
      "spacing_loss": 0.1115674376487732,
      "smoothness_loss": 1.0050090551376343,
      "amplitude_loss": 1.8164159059524536,
      "edge_scale": 0.4897291660308838,
      "spectral_scale": 0.7567309737205505,
      "spectral_shift": -0.006748198997229338
    },
    {
      "step": 2200,
      "loss": 0.06018410623073578,
      "spectral_loss": 0.0003843340964522213,
      "spacing_loss": 0.09663277119398117,
      "smoothness_loss": 0.9641112089157104,
      "amplitude_loss": 1.842274785041809,
      "edge_scale": 0.48497095704078674,
      "spectral_scale": 0.7436100840568542,
      "spectral_shift": 0.001881668227724731
    },
    {
      "step": 2250,
      "loss": 0.053671710193157196,
      "spectral_loss": 0.0003972517733927816,
      "spacing_loss": 0.08431176096200943,
      "smoothness_loss": 0.9251068234443665,
      "amplitude_loss": 1.8675113916397095,
      "edge_scale": 0.4820622205734253,
      "spectral_scale": 0.7425104379653931,
      "spectral_shift": -0.0007399800233542919
    },
    {
      "step": 2300,
      "loss": 0.06870574504137039,
      "spectral_loss": 0.00030556772253476083,
      "spacing_loss": 0.11525344848632812,
      "smoothness_loss": 0.8881232738494873,
      "amplitude_loss": 1.892225980758667,
      "edge_scale": 0.47628137469291687,
      "spectral_scale": 0.7482863664627075,
      "spectral_shift": -0.01144097838550806
    },
    {
      "step": 2350,
      "loss": 0.05810903385281563,
      "spectral_loss": 0.0003817222313955426,
      "spacing_loss": 0.09456277638673782,
      "smoothness_loss": 0.8529542684555054,
      "amplitude_loss": 1.9163801670074463,
      "edge_scale": 0.46971744298934937,
      "spectral_scale": 0.7486028671264648,
      "spectral_shift": -0.004360069986432791
    },
    {
      "step": 2400,
      "loss": 0.06685084104537964,
      "spectral_loss": 0.0003813039802480489,
      "spacing_loss": 0.11267155408859253,
      "smoothness_loss": 0.8193866610527039,
      "amplitude_loss": 1.939895510673523,
      "edge_scale": 0.4641105830669403,
      "spectral_scale": 0.7377030253410339,
      "spectral_shift": 0.0020551811903715134
    },
    {
      "step": 2450,
      "loss": 0.06183084100484848,
      "spectral_loss": 0.0003945921780541539,
      "spacing_loss": 0.10320209711790085,
      "smoothness_loss": 0.7872537970542908,
      "amplitude_loss": 1.9626622200012207,
      "edge_scale": 0.46171191334724426,
      "spectral_scale": 0.7308980226516724,
      "spectral_shift": 0.007537367753684521
    },
    {
      "step": 2500,
      "loss": 0.0822896733880043,
      "spectral_loss": 0.0003807505709119141,
      "spacing_loss": 0.14471380412578583,
      "smoothness_loss": 0.7567254304885864,
      "amplitude_loss": 1.9847650527954102,
      "edge_scale": 0.45772671699523926,
      "spectral_scale": 0.738580584526062,
      "spectral_shift": 0.010540466755628586
    },
    {
      "step": 2550,
      "loss": 0.05797584354877472,
      "spectral_loss": 0.00031608453718945384,
      "spacing_loss": 0.09675516188144684,
      "smoothness_loss": 0.7276008725166321,
      "amplitude_loss": 2.0061707496643066,
      "edge_scale": 0.4534386098384857,
      "spectral_scale": 0.7442326545715332,
      "spectral_shift": 0.0032949906308203936
    },
    {
      "step": 2600,
      "loss": 0.06099977716803551,
      "spectral_loss": 0.00037636293563991785,
      "spacing_loss": 0.10319703072309494,
      "smoothness_loss": 0.6998102068901062,
      "amplitude_loss": 2.026796340942383,
      "edge_scale": 0.45020413398742676,
      "spectral_scale": 0.7296841144561768,
      "spectral_shift": 0.002983947517350316
    },
    {
      "step": 2650,
      "loss": 0.056723009794950485,
      "spectral_loss": 0.00041278789285570383,
      "spacing_loss": 0.09506108611822128,
      "smoothness_loss": 0.6733067035675049,
      "amplitude_loss": 2.0466127395629883,
      "edge_scale": 0.44752004742622375,
      "spectral_scale": 0.7227448225021362,
      "spectral_shift": 0.010162425227463245
    },
    {
      "step": 2700,
      "loss": 0.05291653797030449,
      "spectral_loss": 0.0004023807414341718,
      "spacing_loss": 0.08793402463197708,
      "smoothness_loss": 0.6481366753578186,
      "amplitude_loss": 2.0657784938812256,
      "edge_scale": 0.44068673253059387,
      "spectral_scale": 0.714255690574646,
      "spectral_shift": 0.011433706618845463
    },
    {
      "step": 2750,
      "loss": 0.0654883161187172,
      "spectral_loss": 0.00037345007876865566,
      "spacing_loss": 0.1135825365781784,
      "smoothness_loss": 0.6239596009254456,
      "amplitude_loss": 2.083998203277588,
      "edge_scale": 0.4386857748031616,
      "spectral_scale": 0.7187002301216125,
      "spectral_shift": 0.013719079084694386
    },
    {
      "step": 2800,
      "loss": 0.0562538281083107,
      "spectral_loss": 0.0003452193341217935,
      "spacing_loss": 0.0955955907702446,
      "smoothness_loss": 0.6009374856948853,
      "amplitude_loss": 2.1014394760131836,
      "edge_scale": 0.4344151020050049,
      "spectral_scale": 0.7249608039855957,
      "spectral_shift": 0.005433639511466026
    },
    {
      "step": 2850,
      "loss": 0.06130073964595795,
      "spectral_loss": 0.0003745082067325711,
      "spacing_loss": 0.10603786259889603,
      "smoothness_loss": 0.578924298286438,
      "amplitude_loss": 2.1180579662323,
      "edge_scale": 0.4302458167076111,
      "spectral_scale": 0.7263050079345703,
      "spectral_shift": 0.006992327515035868
    },
    {
      "step": 2900,
      "loss": 0.05213748291134834,
      "spectral_loss": 0.00038235244574025273,
      "spacing_loss": 0.08808393031358719,
      "smoothness_loss": 0.5579307079315186,
      "amplitude_loss": 2.1338584423065186,
      "edge_scale": 0.42481642961502075,
      "spectral_scale": 0.7278369665145874,
      "spectral_shift": -0.0007266116444952786
    },
    {
      "step": 2950,
      "loss": 0.05740706995129585,
      "spectral_loss": 0.00038507365388795733,
      "spacing_loss": 0.09898938983678818,
      "smoothness_loss": 0.5378490686416626,
      "amplitude_loss": 2.1488113403320312,
      "edge_scale": 0.4195415675640106,
      "spectral_scale": 0.7303863763809204,
      "spectral_shift": -0.008358503691852093
    },
    {
      "step": 2999,
      "loss": 0.05221571773290634,
      "spectral_loss": 0.00035064422991126776,
      "spacing_loss": 0.08902397751808167,
      "smoothness_loss": 0.5190463662147522,
      "amplitude_loss": 2.16261887550354,
      "edge_scale": 0.4140271544456482,
      "spectral_scale": 0.7310323715209961,
      "spectral_shift": -0.015460081398487091
    }
  ],
  "note": "Numerical DTES graph operator fitting experiment; not a proof of RH."
}